{
  "nodes":[
    {"name":"MITIGATION-Article 4","group":0, "theme": "mitigation", "linkClass": "Article4"},
    {"name":"NDCs","group":0, "theme": "mitigation", "linkClass": "NDCs"},
    {"name":"Communicate NDCs-4para9","group":0, "theme": "mitigation", "linkClass": "NDCs"},
    {"name":"NDC Public Registry-4para12","group":0, "theme": "mitigation", "linkClass": "Registry"},
    {"name":"Account for NDCs-4para13","group":0, "theme": "mitigation", "linkClass": "NDCs"},
    {"name":"GHG emissions","group":0, "theme": "mitigation", "linkClass": "GHG"},
    {"name":"Reduction Strategies-4para19","group":0, "theme": "mitigation", "linkClass": "Article4"},
    {"name":"Forum II","group":0, "theme": "mitigation", "linkClass": "Forum-II"},
    {"name":"Update every 5 yrs-Decision 23, 24","group":1, "theme": "mitigation", "linkClass": "Article4"},
    {"name":"Submit NDCs in advance-Decision 25","group":1, "theme": "mitigation", "linkClass": "NDCs"},
    {"name":"Ad Hoc Work Grp NDC guidelines-Decision 26","group":1, "theme": "mitigation", "linkClass": "AdHocWorkGrp"},
    {"name":"Secretariat interm version-Decision 30","group":1, "theme": "mitigation", "linkClass": "Secretariat"},
    {"name":"SBI input-Decision 29","group":1, "theme": "mitigation", "linkClass": "SBI"},
    {"name":"Secretariat publish online-Decision 36","group":1, "theme": "mitigation", "linkClass": "Secretariat"},
    {"name":"Ad Hoc Work Grp guidance-Decision 31","group":1, "theme": "mitigation", "linkClass": "AdHocWorkGrp"},
    {"name":"SBSTA recommendations-Decision 34","group":1, "theme": "mitigation", "linkClass": "SBSTA"},
    {"name":"SBI recommendations-Decision 34","group":1, "theme": "mitigation", "linkClass": "SBI"}
  ],
  "links":[
    {"source":0,"target":1,"value":4},
    {"source":1,"target":2,"value":4},
    {"source":1,"target":3,"value":4},
    {"source":1,"target":4,"value":4},
    {"source":0,"target":5,"value":4},
    {"source":5,"target":6,"value":4},
    {"source":0,"target":7,"value":4},
    {"source":2,"target":8,"value":4},
    {"source":1,"target":9,"value":4},
    {"source":1,"target":10,"value":4},
    {"source":3,"target":11,"value":4},
    {"source":3,"target":12,"value":4},
    {"source":6,"target":13,"value":4},
    {"source":4,"target":14,"value":4},
    {"source":7,"target":15,"value":4},
    {"source":7,"target":16,"value":4}
  ]
}